dictquery/__init__.py
dictquery/datavalue.py
dictquery/exceptions.py
dictquery/parsers.py
dictquery/tokenizer.py
dictquery/visitors.py
dictquery-0.5.0.dist-info/LICENSE
dictquery-0.5.0.dist-info/METADATA
dictquery-0.5.0.dist-info/WHEEL
dictquery-0.5.0.dist-info/top_level.txt
dictquery-0.5.0.dist-info/RECORD
